pyrothermel_bindings.cp312-win_amd64.pyd
pyrothermel-0.0.5.dist-info/METADATA
pyrothermel-0.0.5.dist-info/WHEEL
pyrothermel-0.0.5.dist-info/top_level.txt
pyrothermel-0.0.5.dist-info/RECORD
