Metadata-Version: 2.4
Name: pyrothermel
Version: 0.0.5
Summary: Python bindings and API for Behave extended Rothermel fire models
Home-page: https://github.com/j-tenny/pyrothermel
Author: Johnathan Tenny
Author-email: jt893@nau.edu
License: MIT
Classifier: Programming Language :: Python :: 3
Classifier: Programming Language :: C++
Classifier: License :: OSI Approved :: MIT License
Classifier: Operating System :: OS Independent
